llm_embed_hazo.py
llm_embed_hazo-0.2.1.dist-info/LICENSE
llm_embed_hazo-0.2.1.dist-info/METADATA
llm_embed_hazo-0.2.1.dist-info/WHEEL
llm_embed_hazo-0.2.1.dist-info/entry_points.txt
llm_embed_hazo-0.2.1.dist-info/top_level.txt
llm_embed_hazo-0.2.1.dist-info/RECORD
