Metadata-Version: 2.1
Name: llm-embed-hazo
Version: 0.2.1
Summary: Dummy llm plugin for demonstration purposes
Author: Florents Tselai
License: Apache-2.0
Project-URL: Homepage, https://github.com/Florents-Tselai/llm-embed-hazo
Project-URL: Changelog, https://github.com/Florents-Tselai/llm-embed-hazo/releases
Project-URL: Issues, https://github.com/Florents-Tselai/llm-embed-hazo/issues
Project-URL: CI, https://github.com/Florents-Tselai/llm-embed-hazo/actions
Classifier: License :: OSI Approved :: Apache Software License
License-File: LICENSE
Requires-Dist: llm
Requires-Dist: transformers
Requires-Dist: torch
Provides-Extra: test
Requires-Dist: pytest ; extra == 'test'
